dataset_csv_generator/__init__.py
dataset_csv_generator/about.py
dataset_csv_generator/desktop.py
dataset_csv_generator/prog_csv_gen.py
dataset_csv_generator/prog_csv_gen_gui.py
dataset_csv_generator/prog_csv_split_gui.py
dataset_csv_generator/icons/logo.png
dataset_csv_generator/modules/__init__.py
dataset_csv_generator/modules/configure.py
dataset_csv_generator/modules/wabout.py
dataset_csv_generator-0.1.0.dist-info/licenses/LICENSE
dataset_csv_generator-0.1.0.dist-info/METADATA
dataset_csv_generator-0.1.0.dist-info/WHEEL
dataset_csv_generator-0.1.0.dist-info/entry_points.txt
dataset_csv_generator-0.1.0.dist-info/top_level.txt
dataset_csv_generator-0.1.0.dist-info/RECORD
